neoloom/__init__.py
neoloom/db.py
neoloom/mappers.py
neoloom/proxy.py
neoloom/query.py
neoloom/relationships.py
neoloom/repository.py
neoloom/serializers.py
neoloom/session.py
neoloom/fields/__init__.py
neoloom/fields/base.py
neoloom/fields/node.py
neoloom/fields/relation.py
neoloom/nodes/__init__.py
neoloom/nodes/meta.py
neoloom/nodes/node.py
neoloom-0.1.0.dist-info/METADATA
neoloom-0.1.0.dist-info/WHEEL
neoloom-0.1.0.dist-info/licenses/LICENSE
neoloom-0.1.0.dist-info/RECORD
