Metadata-Version: 2.4
Name: neoloom
Version: 0.1.0
Summary: A lightweight Data Mapper-based OGM for Neo4j with Unit of Work, Repository, and Query Builder
Project-URL: Homepage, https://github.com/yourname/neoloom
Project-URL: Repository, https://github.com/yourname/neoloom
Author-email: Amirhossein Faghihifar <a.faghihifar@gmail.com>
License: MIT
License-File: LICENSE
Keywords: data-mapper,graph,neo4j,ogm,orm
Classifier: Development Status :: 3 - Alpha
Classifier: Intended Audience :: Developers
Classifier: License :: OSI Approved :: MIT License
Classifier: Programming Language :: Python
Classifier: Programming Language :: Python :: 3
Classifier: Programming Language :: Python :: 3.9
Classifier: Programming Language :: Python :: 3.10
Classifier: Programming Language :: Python :: 3.11
Classifier: Topic :: Database
Requires-Python: >=3.10
Requires-Dist: neo4j>=5.0
